{
  "Холод Флора": [false
    ,"бифидумбактерин"
    ,"лактобактерин"
    ,"нормоспектрум"
    ,"пробифор"
    ,"флорин"
    ,"бифилиз"
    ,"примадофилус"
    ,"аципол"
    ,"йогулакт"
    ,"наринэ"
    ,"вагилак"
    ,"нормофлорин"
    ,"бактериофаг сальмонелезный"
    ,"пиобактериофаг комплексный"
    ,"колипротейный бактериофаг"
    ,"интести бактериофаг" 
     ,"пиобактериофаг "
    ,"имуноглобулиновый комплекс кип"
    ,"стафилококковый бактериофаг"
    ,"стрептококковый бактериофаг"
    ,"пиобактериофаг поливалентный очищенный"
  ],
  "1хр1": [false
    ,"синекод"
    ,"панатус"
    ,"суприма бронхо"
    ,"трависил"
    ,"линкас"
    ,"бронхобосс"
    ,"бронхинол"
    ,"доктор мом"
    ,"кашлестопы"
    ,"алтея"
    ,"ренгалин"
  ],
  "1хр2": [false
    ,"янтарная кислота"
    ,"магне в6"
    ,"магнелис"
    ,"витамин Е"
    ,"витамин А"
    ,"аевит"
    ,"акнекутан"
    ,"вигантол"
    ,"аквадетрим"
    ,"бебисан д3"
    ,"дсан вит д"
    ,"альфа-токоферола ацетат масляный"
  ],
  "1хр3": [false
    ,"галавит"
    ,"ликопид"
    ,"арбидол"
    ,"бронхо-мунал"
    ,"глицерам"
    ,"исмиген"
    ,"ингавирин"
    ,"полиоксидоний"
    ,"цитовир"
    ,"орвирем"
    ,"оциллококцинум"
    ,"тамифлю"
    ,"цитовир"
    ,"циклоферон"
    ,"анаферон"
    ,"эргоферон"
    ,"иммунал"
    ,"ацикловир"
    ,"фамвир"
    ,"валцекон"
    ,"валвир"
    ,"валтрекс"
    ,"имунорикс"
    ,"агри"
    ,"реленза"
    ,"кагоцел"
    ,"амиксин"
    ,"гроприносин"
    ,"изопринозин"
    ,"эффералган сироп"
    ,"нурофен сироп"
  ],
  "1хр4": [false
    ,"диклофенак"
    ,"ортофен"
    ,"артрокер"
    ,"диафлекс"
    ,"вальтарен"
    ,"аэртал"
    ,"кетонал"
    ,"индометацин"
    ,"суматриптан"
    ,"сумамигрен"
    ,"амигренин"
    ,"релпакс"
    ,"оки"
    ,"плаквенил"
    ,"дилакса"
    ,"бутадион"
    ,"пиаскледин"
    ,"диартрин"
    ,"артродарин"
    ,"артрозилен"
    ,"фламакс"
    ,"вольтарен"
  ],
  "1хр5": [false
    ,"аркоксиа"
    ,"кеторол"
    ,"найз"
    ,"нимесил"
    ,"ибупрофен"
    ,"пироксикам"
    ,"целебрекс"
    ,"сирдалуд"
    ,"тизанидин"
    ,"тизалуд"
    ,"мидокалм"
    ,"нимулид"
    ,"мовалис"
    ,"апонил"
    ,"найзилат"
    ,"мелоксикам"
    ,"мовасин"
    ,"артрозан"
    ,"амелотекс"
    ,"ксефокам"
  ],
  "1хр6": [false
    ,"терафлекс"
    ,"артра"
    ,"дона"
    ,"структум"
    ,"хондроитин"
    ,"геладринк"
  ],
  "2хр": [false
    ,"амбробене"
    ,"бромгексин"
    ,"лазолван"
    ,"флюдитек"
    ,"гербион"
    ,"флуифорт"
    ,"либексин муко"
  ],
  "2хр2": [false
    ,"амброгексал"
    ,"стодаль"
    ,"аскорил"
    ,"флавамед"
    ,"кленбутерол"
    ,"джосет"
    ,"туссамаг"
    ,"алтея сироп"
    ,"доктор мом"
    ,"бронхикум с"
    ,"коделак"
    ,"стоптуссин"
    ,"эреспал"
    ,"проспан"
    ,"сиресп"
    ,"эриспирус"
  ],
  "2хр3": [false
    ,"ацц"
    ,"термопсол"
    ,"флуимуцил"
    ,"ацетилцистеин"
    ,"флуифорт"
    ,"бромгексин"
    ,"линкас лор"
    ,"геломиртол"
    ,"таблетки от кашля"
    ,"либексин"
    ,"халиксол"
    ,"ренгалин"
    ,"омнитус"
    ,"эладон"
    ,"трависил"
  ],
  "2хр4": [false
    ,"лизобакт"
    ,"имудон"
    ,"гексализ"
    ,"нео-ангин"
    ,"стрепсилс"
    ,"гексорал табс"
    ,"эвкалипт"
    ,"шалфей"
    ,"мукоплант"
    ,"антиангин"
    ,"септолетте"
    ,"тантум верде"
    ,"терафлю лар"
    ,"граммидин"
    ,"ларипронт"
  ],
  "2хр5": [false
    ,"феррум лек"
    ,"актиферин"
    ,"мальтофер"
    ,"ферлатум"
    ,"тотема"
    ,"фенюльс"
    ,"ферретаб"
    ,"тардиферрон"
    ,"элевит пронаталь"
    ,"витрум пренаталь"
    ,"компливит триместрум"
    ,"пентовит"
    ,"сорбифер дурулес"
    ,"фолио"
    ,"фолацин"
    ,"нейробион"
    ,"мильгамма"
    ,"комбилипен"
    ,"пиридоксина гидрохлорид"
    ,"никотиновая кислота"
    ,"фолибер"
    ,"аскорутин"
    ,"фолиевая кислота"
  ],
  "2хр6": [false
    ,"нимулид"
    ,"нурофен сироп"
    ,"панадол сироп"
    ,"максиколд сироп"
    ,"микстура от кашля сухая"
  ],
  "4хр1": [false
    ,"анауран"
    ,"ацерумен"
    ,"ремовакс"
    ,"полидекса уши"
    ,"отофа"
    ,"комбинил"
    ,"отирелакс"
    ,"отинум"
    ,"нормакс"
    ,"ципромед"
    ,"отипакс"
  ],
  "4хр2": [false
    ,"арутимол"
    ,"альфаган"
    ,"азарга"
    ,"азопт"
    ,"бетофтан"
    ,"бетоптик"
    ,"ганфорт"
    ,"дорзопт"
    ,"трусопт"
    ,"дуотрав"
    ,"комбиган"
    ,"косопт"
    ,"траватан"
    ,"тимолол"
    ,"окумет"
  ],
  "4хр3": [false
    ,"неванак"
    ,"витабакт"
    ,"окомистин"
    ,"вигамокс"
    ,"дикло-ф"
    ,"данцил"
    ,"декса-гентамицин капли"
    ,"броксинак"
    ,"макситрол"
    ,"максидекс"
    ,"офтаквикс"
    ,"сигницеф"
    ,"тобрадекс"
    ,"тобрекс"
    ,"тобразон"
    ,"ципрофлоксацин"
    ,"цинка сульфат"
    ,"ципролет"
    ,"дексаметазон капли"
    ,"колбиоцин мазь"
    ,"солкосерил мазь гл"
    ,"вита-пос"
    ,"видисик"
    ,"флоксал"
    ,"корнерегель"
    ,"фуциталмик"
    ,"декса-гентамицин мазь"
    ,"зовиракс мазь гл"
    ,"ацикловир мазь гл"
    ,"демозол крем косметический"
  ],
  "4хр4": [false
    ,"тайфон таурин"
    ,"тагель"
    ,"артелак"
    ,"оптив"
    ,"хилокомод"
    ,"хилозаркомод"
    ,"видкомод"
    ,"хилопаринкомод"
    ,"хиломакскомод"
    ,"окуметил"
    ,"катионорм"
    ,"визин"
    ,"октилия"
    ,"лекролин"
    ,"аллергодил"
    ,"ирифрин"
    ,"каталин"
    ,"кромогексал"
    ,"опатанол"
    ,"офтагель"
    ,"блефарогель"
    ,"блефаролосьон"
    ,"баларпан"
    ,"полинадим"
    ,"слеза натуральная"
    ,"эмоксипин"
    ,"визоптик"
    ,"дефислед"
    ,"актипол"
    ,"слезин"
    ,"офтолик"
    ,"оптифри"
    ,"стиллавит"
    ,"оксиал"
    ,"визин"
    ,"систеин"
  ],
  "4хр5": [false
    ,"авамис"
    ,"алергодил"
    ,"дезринит"
    ,"кромогексал"
    ,"назаваль"
    ,"насобек"
    ,"назарел"
    ,"момат рино"
    ,"тафен назаль"
    ,"фликсоназе"
    ,"назонекс"
    ,"эуфорбиум композиткм"
    ,"люффель"
  ],
  "5хр1": [false
    ,"йодбаланс"
    ,"йкалия йодид"
    ,"йодомарин"
    ,"тирозол"
    ,"л-тироксин"
    ,"эутирокс"
    ,"метипред"
    ,"метилпреднизолон"
  ],
  "5хр2": [false
    ,"дибикор"
    ,"глюкофаж"
    ,"метформин"
    ,"галвус"
    ,"тиоктацид"
    ,"октолипен"
    ,"тиогамма"
    ,"липоевая кислота"
    ,"берлитион"
    ,"глибомет"
    ,"сиофор"
  ],
  "5хр3": [false
    ,"манинил"
    ,"амарил"
    ,"янувия"
    ,"онглиза"
    ,"бетмига"
    ,"диабетон"
    ,"форсига"
    ,"янумет"
    ,"тражента"
    ,"новонорм"
    ,"глюкованс"
    ,"глюренорм"
    ,"диамерид"
    ,"комбоглиз пролонг"
  ],
  "5хр4": [false
    ,"атаракс гидроксизин"
    ,"адепресс пароксетин"
    ,"асентра сентралин"
    ,"амитриптилин"
    ,"азафен пипофезин"
    ,"адаптол тетраметилтетраазобициклооктандион"
    ,"анвифен аминофенилмасляная кислота"
    ,"аминазин хлорпромазин"
    ,"анафранил кломипрамин"
    ,"вальдоксан агомелатин"
    ,"велаксен венлафаксин"
    ,"грандаксин тофизопан"
    ,"галоперидол"
    ,"вальпарин вальпроевая кислота"
    ,"рексетин пароксетин"
    ,"стрезам этифоксин"
    ,"прозак флуоксетин"
    ,"пиразидол пирлиндол"
    ,"пропазин промазин"
    ,"неулептил перициазин"
    ,"мирапекс прамипексол"
    ,"лерибон миансерин"
    ,"зипрекса оланзапин"
    ,"золофт сертралин"
    ,"сонапакс тиоридазин"
    ,"сероквель кветиапин"
    ,"селектра эсциталопрам"
    ,"серената сертралин"
    ,"симбалта дулоксетин"
    ,"сиозам циталопрам"
    ,"страттера атомокситин"
    ,"ремерон миртазопин"
    ,"рисполепт рисперидон"
  ],
  "5хр5": [false
    ,"паксил пароксетин"
    ,"тебантин габапентин"
    ,"конвалис габапентин"
    ,"праноран пирибедил"
    ,"ламиктал ламотриджин"
    ,"ципралекс эсциталопрам"
    ,"ципрамил циталопрам"
    ,"эглонил сульпирид"
    ,"эйсипи эсциталопрам"
    ,"этаперазин перфеназин"
    ,"димедрон дифенгидрамин"
    ,"флюанксол флупентиксол"
    ,"тетурам дисульфирам"
    ,"трифтазин трифлуоперазин"
    ,"тиорил тиоридазин"
    ,"триттико тразодон"
    ,"тералиджен алимемазин"
    ,"фенозепам бромдигидроклорфенилбензодиазепин"
    ,"фенибут аминофенилмасляная кислота"
    ,"флуоксетин "
    ,"феварин флувоксамин"
    ,"труксал хлорпротиксен"
    ,"хлорпротиксен"
  ],
  "5хр6": [false
    ,"тидомет форте "
    ,"пк-мерц"
    ,"амантадин"
    ,"наком леводопа+"
    ,"нейромидин ипидакрин"
    ,"карбамазепин"
    ,"финлепсин карбамазепин"
    ,"топамакс топирамат"
    ,"конвулекс вальпроевая кислота"
    ,"кеппра леверитацетам"
    ,"тегретол карбамазепин"
    ,"трилептал окскарбазепин"
    ,"аксамон ипидакрин"
    ,"ламетор ламотриджин"
    ,"мадопар леводопа"
    ,"экселон ривастигмин"
  ],
  "6хр1": [false
    ,"аторвастатин"
    ,"аторис аторвастатин"
    ,"липримар аторвастатин"
    ,"торвакард аторвастатин"
    ,"тулип аторвастатин"
  ],
  "6хр2": [false
    ,"эналаприл"
    ,"берлиприл эналаприл "
    ,"энап"
    ,"энам"
    ,"ко-ренитек эналаприл"
    ,"рениприл эналаприл"
    ,"энзикс дуо эналаприл"
    ,"капотен"
    ,"каптоприл"
    ,"капозид"
  ],
  "6хр3": [false
    ,"атенолол"
    ,"локрен бетаксолол"
    ,"тенорик атенолол+"
    ,"дилатренд карведилол"
    ,"карведилол"
    ,"арител бисопролол"
    ,"биол бисопролол"
    ,"кординорм бисопролол "
    ,"бипрол бисопролол"
    ,"коронал бисопролол"
    ,"конкор бисопролол"
    ,"бисогамма бисопролол"
    ,"небилол"
    ,"лодоз бисопролол+"
    ,"небилет небиволол"
    ,"метопролол"
    ,"беталок метопролол"
    ,"эгилок метопролол"
    ,"нипертен бисопролол"
    ,"бисопролол"
  ],
  "6хр4": [false
    ,"амлодипин"
    ,"калчек амлодипин"
    ,"амлотоп амлодипин"
    ,"эскордикор амлодипин"
    ,"нормодипин амлодипин"
    ,"кардилапин амлодипин"
    ,"амловаз амлодипин"
    ,"аттенто амлодипин+омесартан"
    ,"норваск амлодипин"
    ,"тенокс амлодипин"
    ,"эгипрес амлодипин+рамиприл"
    ,"фелодип фелодипин"
    ,"нифекард нифедипин"
    ,"кордипин нифедипин"
    ,"кальцигард нифедипин"
    ,"плендил фелодипин"
    ,"кодафлекс нифедипин"
    ,"коринфар нифедипин"
    ,"леркамен лерканидипин"
    ,"этацизин диэтиламинопропионилэтоксикарбониламинофенотиазин"
    ,"занидип лерканидипин"
    ,"кординик никорандил"
    ,"экватор амлодипин+лизиноприл"
  ],
  "6хр5": [false
    ,"кардикет изосорбида динитрат"
    ,"эфокс изосорбида динитрат"
    ,"пектрол изосорбида динитрат"
    ,"нитроминт нитроглицерин"
    ,"изокет изосорбида динитрат"
    ,"моносан изосорбида мононитрат"
    ,"верапамил"
    ,"эринит"
    ,"допегит метилдопа"
    ,"нитроглицерин"
    ,"аллапинин"
    ,"сиднофарм молсидомин"
    ,"моночинкве изосорбида мононитрат"
    ,"новокаинамид прокаинамид"
    ,"сотагексал соталол"
    ,"кордарон амиодарон"
    ,"амиодарон"
    ,"дилтиазем"
    ,"изоптин верапамил"
    ,"тарка верапамил+трандолаприл"
    ,"пропанорм пропафенон "
    ,"ритмонорм пропафенон"
    ,"анаприлин"
  ],
  "7хр1": [false
    ,"зокор симвастатин"
    ,"вазилип симвастатин"
    ,"симвагексал симвастатин"
    ,"симвастатин"
    ,"трайкор фенофибрат"
    ,"омакор омега 3"
    ,"эзетрол эзетимиб"
    ,"микардис телмисартан"
  ],
  "7хр2": [false
    ,"фозикард фозиноприл"
    ,"амприлан рамиприл"
    ,"моноприл фозиноприл"
    ,"тритаце рамиприл"
    ,"аккупро хинаприл"
    ,"ирузид лизиноприл+гидрохлоротиазид"
    ,"лизинотон лизиноприл"
    ,"альбарел рилминидил"
    ,"лизиноприл"
    ,"моксарел моксонидин"
    ,"моксонидин"
    ,"моксонитекс моксонидин"
    ,"физиотенз моксонидин"
    ,"лизиноприл"
    ,"диротон лизиноприл"
    ,"кодиротон лизиноприл+гидрохлоротиазид"
    ,"хартил рамиприл"
    ,"хартил д рамиприл+гидрохлоротиазид"
    ,"пирамил рамиприл"
  ],
  "7хр3": [false
    ,"лоза плюс лозартан+гидрохлоротиазид"
    ,"лозап лозартан"
    ,"гипосарт кандесартан"
    ,"лозартан"
    ,"лориста лозартан"
    ,"лориста н лозартан+гидрохлоротиазид"
    ,"эдарби азисартан"
    ,"эдарби кло азисартан+хлорталидон"
    ,"диован валсартан"
    ,"кодиован валсартан+гидрохлоротиазид"
    ,"вальсакор валсартан+гидрохлоротиазид"
    ,"эксфорж амлодипин+валсартан"
    ,"лозарел лозартан"
    ,"лозарел плюс лозартан+гидрохлоротиазид"
    ,"телзап телмисартан"
    ,"козаар лозартан"
    ,"атаканд кандесартан"
    ,"одрисс кандесартан"
    ,"апровель ирбисартан"
    ,"коапровель ирбесартан+гидрохлоротиазид"
    ,"кардосал олмесартан"
    ,"кардосал плюс олмесартан+гидрохлотиазид"
    ,"теветен эпросартан"
    ,"теветен плюс эпросартан+гидрохлоротиазид"
  ],
  "7хр4": [false
    ,"ранекса ранулозин"
    ,"предуктал триметазидин"
    ,"депренорм триметазидин"
    ,"тримектал триметазидин"
    ,"триметазидин "
    ,"магнерот магния оротат"
    ,"панангин калий+магний"
    ,"магнемакс магния оротат"
    ,"рибоксин инозин"
    ,"кораксан ивабрадин"
    ,"зокардис зофеноприл"
    ,"римекор триметазидин"
    ,"калия оротат "
    ,"норматенз резерпин"
    ,"аспаркам"
  ],
  "7хр5": [false
    ,"эгитромб клопидогрел"
    ,"ксарелто ривароксабан"
    ,"курантил дипирадамол"
    ,"фенилин фениндион"
    ,"лопирел клопидогрел"
    ,"варфарин"
    ,"зилт клопидогрел"
    ,"плагрил клопидогрел"
    ,"прадакса дабиготрана этаксилат"
  ],
  "8хр1": [false
    ,"тевастор розувастатин"
    ,"роксера розувастатин"
    ,"розарт розувастатин"
    ,"розулип розувастатин"
    ,"сувардио розувастатин"
    ,"мертенил розувастатин"
    ,"розукард розувастатин"
    ,"крестор розувастатин"
  ],
  "8хр2": [false
    ,"периндоприл"
    ,"дальнева периндоприл+амлодипин"
    ,"кодальнева периндоприл+амлодипин+индапамид"
    ,"перинева периндоприл"
    ,"коперинева периндоприл+индапамид"
    ,"престанс периндоприл+амлодипин"
    ,"нолипрел периндоприл+индапамид"
    ,"престариум периндоприл"
    ,"трипликсам амодипин+индапамид+периндоприл"
  ],
  "8хр3": [false
    ,"тромбоасс"
    ,"кардиаск"
    ,"ацекардол"
    ,"аспирин кардио"
    ,"аспикор"
    ,"тромбитал"
    ,"кардиомагнил"
  ],
  "8хр4": [false
    ,"верошпиронолактон спиронолактон"
    ,"верошпирон спиронолактон"
    ,"индапамид"
    ,"биакарб ацетазоламид"
    ,"тригрим торасемид"
    ,"лазикс фуросемид"
    ,"фуросемид"
    ,"торасемид"
    ,"диувер торасемид"
    ,"бритомар торасемид"
    ,"гипотиазид гидрохлоротиазид"
    ,"триампур триамтерен+гидрохлоротиазид"
    ,"индап индапамид"
    ,"индапамид"
    ,"инспра эплеренон"
    ,"лавер ср индапамид"
    ,"арифон индапамид"
  ],
  "8хр5": [false
    ,"аллопуринол"
    ,"уронормин монурал"
    ,"монурал"
    ,"блемарен"
    ,"пролит суперкапсулы"
    ,"уролесан"
    ,"уротол"
    ,"леспефрил"
    ,"леспефлан"
    ,"урокам"
    ,"цистон"
    ,"фитолизин"
    ,"фурамаг"
    ,"палин"
    ,"фурадонин"
    ,"фурагин"
    ,"норбактин"
    ,"нолицин"
    ,"нитроксолин"
    ,"5нок"
    ,"везикар"
    ,"спазмекс"
    ,"роватинекс"
    ,"дриптан"
  ], 
  "холод 1 2-8* 1": [false
    ,"алломедин гель"
    ,"виферон мазь"
    ,"герпферон"
    ,"эритромицин мазь"
    ,"тетрациклин мазь гл"
    ,"оксолин"
    ,"нистатин"
  ],
  "холод 1 2-8* 2": [false
    ,"семакс"
    ,"пилокарпин"
    ,"алкаин"
    ,"ксалатамакс"
    ,"ксалатан"
    ,"глаупрост"
    ,"дуопрост"
    ,"фотил"
    ,"дексаметазон офтан"
    ,"кандибиотик капли ушные"
    ,"офтальмоферрон"
    ,"офтан катахром"
    ,"визомитин"
    ,"сульфацил натрия"
    ,"левомицетин капли гл"
    ,"ксалаком"
  ],
  "холод 1 2-8* 3": [false
    ,"мильгамма амп"
    ,"мидокалм амп"
    ,"нейромультивит амп"
    ,"комбилипен амп"
    ,"нейрогамма амп"
    ,"комплигам амп"
    ,"иммунофан амп"
    ,"полиоксидоний амп"
    ,"лонгидаза амп"
  ],
  "холод 1 2-8* 4": [false
    ,"виферон св"
    ,"панавир св"
    ,"полиоксидоний св"
    ,"иммунофан св"
  ],
  "холод 1 2-8* 5": [false
    ,"генферон св"
    ,"новаринг кольцо"
    ,"тыквеол св"
    ,"полиоксидоний св"
    ,"лонгидаза св"
    ,"гинофлор э св"
    ,"лактонорм"
    ,"ацелакт св"
    ,"редецил мазь"
    ,"радевит мазь"
    ,"уродерм мазь"
    ,"ретиноевая мазь"
  ],
  "холод 1 2-8* 6": [false
    ,"деринат капли"
    ,"гриппферон капли"
    ,"генферон лайт капли"
    ,"мультитабс от 0 до 1года витамины АСД"
    ,"интерферон"
    ,"имуномакс"
  ],
  "холод 1 2-8* низ": [false
    ,"миокальцик"
    ,"простакор"
    ,"даларгин"
    ,"тактивин"
    ,"имуноглобулин"
    ,"панавир св"
    ,"эссенциале амп"
    ,"натрия аденозин трифосфат"
    ,"новорапид"
    ,"актропид"
    ,"кипферон св"
    ,"протафан"
  ],
  "холод 2 8-15* 1": [false
    ,"гепатосан"
    ,"энтеросан"
    ,"ацидин-пепсин"
    ,"валидол капс"
    ,"мятные таб"
    ,"пектуссин таб"
  ],
  "холод 2 8-15* 2": [false
    ,"льняное масло"
    ,"масло расторопши"
    ,"облепиховое масло жид"
    ,"холосас"
    ,"рыбий жир жид"
    ,"каланхоэ сок"
    ,"алоэ сок"
    ,"шиповника масло"
    ,"облепиховое масло"
    ,"бефунгин р-р"
    ,"подорожника сок"
    ,"зеленина капли"
    ,"карниланд"
  ],
  "холод 2 8-15* 3": [false
    ,"закофальк"
    ,"родиолы экстракт"
    ,"линкомицин капс"
    ,"апилак"
    ,"ликолам"
    ,"омегатрин"
    ,"марены экстракт таб"
    ,"океанол"
    ,"фенигидин нифедипин"
    ,"эссенциале капс"
    ,"пиона настойка"
    ,"женьшеня настойка"
    ,"бейбикалм"
  ],
  "холод 2 8-15* 4": [false
    ,"карипазим"
    ,"люголя р-р с глицерином"
    ,"ретинола ацетат вит А жид"
    ,"ретинола пальмитат вит А жид"
    ,"хлорофиллипт"
    ,"панкреатин"
    ,"аекол"
    ,"томицид"
  ],
  "холод 2 8-15* 5": [false
    ,"цефекон"
    ,"корилип"
    ,"корилип нео"
    ,"прополис мазь"
    ,"алпизарин мазь"
    ,"скипидарная мазь"
  ],
  "холод 2 8-15* низ": [false
    ,"пустырника настойка"
    ,"мукалтин"
    ,"солодки сироп"
    ,"пертуссин сироп"
  ],
  "холод 3 8-15* 1": [false
    ,"прополис нд св"
    ,"биопрост "
    ,"витапрост св"
    ,"простатилен св"
    ,"бетадин св"
    ,"триожиналь"
    ,"гамамелис св"
  ],
  "холод 3 8-15* 2": [false
    ,"диклофенак св"
    ,"анестезол"
    ,"ихтиол св"
    ,"новокаин св"
    ,"нистатин св"
    ,"депантол св"
    ,"нигепан св"
    ,"неоанузол св"
    ,"папаверин св"
    ,"красавка св"
    ,"бетиол св"
  ],
  "холод 3 8-15* 3": [false
    ,"серная мазь"
    ,"микозорал"
    ,"гентамицин мазь"
    ,"аргосульфан"
    ,"ихтиол мазь"
    ,"фунготербин  мазь"
    ,"салициловая мазь"
    ,"метилурацил"
    ,"левосин"
    ,"синтомицин"
    ,"синафлан"
    ,"стрептоцид мазь"
    ,"ауробин"
  ],
  "холод 3 8-15* 4": [false
    ,"хондроитин-акос"
    ,"фторокорт"
    ,"диклофенак мазь"
    ,"бутадион мазь"
    ,"бомбенге"
    ,"диоксидин мазь"
    ,"синтомицин мазь"
    ,"гепариновая мазь"
    ,"имофераза"
    ,"гидрокортизон"
    ,"клотримазол мазь"
  ],
  "холод 3 8-15* 5": [false
    ,"ницерголин"
    ,"мукосат"
    ,"хондролон"
    ,"мексиприм"
    ,"кокарбоксилаза"
    ,"амикацин"
  ],
  "холод 3 8-15* 6": [false
    ,"натрия тиосульфат"
    ,"окситоцин"
    ,"кокарбоксилаза"
    ,"химотрипсин"
    ,"цитохром"
    ,"лидаза"
    ,"гонадотропин хорионический"
    ,"деринат амп"
    ,"адреналин амп"
  ],
  "холод 3 8-15* низ": [false
    ,"левомеколь"
    ,"гепариновая мазь"
    ,"скинкап"
    ,"желчь"
    ,"олазоль"
    ,"гидроперит"
    ,"теймурова паста"
    ,"преднизолон"
    ,"ибупрофен мазь"
  ]
}